<?xml version="1.0"?>
<Interface Version="1" Minor="1">
	<Ifc Id="ROOT" Top="1">
		<Bus Id="FlashData">
			<Port Id="15" Dir="INOUT"/>
			<Port Id="14" Dir="INOUT"/>
			<Port Id="13" Dir="INOUT"/>
			<Port Id="12" Dir="INOUT"/>
			<Port Id="11" Dir="INOUT"/>
			<Port Id="10" Dir="INOUT"/>
			<Port Id="9" Dir="INOUT"/>
			<Port Id="8" Dir="INOUT"/>
			<Port Id="7" Dir="INOUT"/>
			<Port Id="6" Dir="INOUT"/>
			<Port Id="5" Dir="INOUT"/>
			<Port Id="4" Dir="INOUT"/>
			<Port Id="3" Dir="INOUT"/>
			<Port Id="2" Dir="INOUT"/>
			<Port Id="1" Dir="INOUT"/>
			<Port Id="0" Dir="INOUT"/>
		</Bus>
		<Bus Id="Ram1Data">
			<Port Id="15" Dir="INOUT"/>
			<Port Id="14" Dir="INOUT"/>
			<Port Id="13" Dir="INOUT"/>
			<Port Id="12" Dir="INOUT"/>
			<Port Id="11" Dir="INOUT"/>
			<Port Id="10" Dir="INOUT"/>
			<Port Id="9" Dir="INOUT"/>
			<Port Id="8" Dir="INOUT"/>
			<Port Id="7" Dir="INOUT"/>
			<Port Id="6" Dir="INOUT"/>
			<Port Id="5" Dir="INOUT"/>
			<Port Id="4" Dir="INOUT"/>
			<Port Id="3" Dir="INOUT"/>
			<Port Id="2" Dir="INOUT"/>
			<Port Id="1" Dir="INOUT"/>
			<Port Id="0" Dir="INOUT"/>
		</Bus>
		<Bus Id="Ram2Data">
			<Port Id="15" Dir="INOUT"/>
			<Port Id="14" Dir="INOUT"/>
			<Port Id="13" Dir="INOUT"/>
			<Port Id="12" Dir="INOUT"/>
			<Port Id="11" Dir="INOUT"/>
			<Port Id="10" Dir="INOUT"/>
			<Port Id="9" Dir="INOUT"/>
			<Port Id="8" Dir="INOUT"/>
			<Port Id="7" Dir="INOUT"/>
			<Port Id="6" Dir="INOUT"/>
			<Port Id="5" Dir="INOUT"/>
			<Port Id="4" Dir="INOUT"/>
			<Port Id="3" Dir="INOUT"/>
			<Port Id="2" Dir="INOUT"/>
			<Port Id="1" Dir="INOUT"/>
			<Port Id="0" Dir="INOUT"/>
		</Bus>
		<Bus Id="Ram2Addr">
			<Port Id="17" Dir="OUT"/>
			<Port Id="16" Dir="OUT"/>
			<Port Id="15" Dir="OUT"/>
			<Port Id="14" Dir="OUT"/>
			<Port Id="13" Dir="OUT"/>
			<Port Id="12" Dir="OUT"/>
			<Port Id="11" Dir="OUT"/>
			<Port Id="10" Dir="OUT"/>
			<Port Id="9" Dir="OUT"/>
			<Port Id="8" Dir="OUT"/>
			<Port Id="7" Dir="OUT"/>
			<Port Id="6" Dir="OUT"/>
			<Port Id="5" Dir="OUT"/>
			<Port Id="4" Dir="OUT"/>
			<Port Id="3" Dir="OUT"/>
			<Port Id="2" Dir="OUT"/>
			<Port Id="1" Dir="OUT"/>
			<Port Id="0" Dir="OUT"/>
		</Bus>
		<Bus Id="FlashAddr">
			<Port Id="22" Dir="OUT"/>
			<Port Id="21" Dir="OUT"/>
			<Port Id="20" Dir="OUT"/>
			<Port Id="19" Dir="OUT"/>
			<Port Id="18" Dir="OUT"/>
			<Port Id="17" Dir="OUT"/>
			<Port Id="16" Dir="OUT"/>
			<Port Id="15" Dir="OUT"/>
			<Port Id="14" Dir="OUT"/>
			<Port Id="13" Dir="OUT"/>
			<Port Id="12" Dir="OUT"/>
			<Port Id="11" Dir="OUT"/>
			<Port Id="10" Dir="OUT"/>
			<Port Id="9" Dir="OUT"/>
			<Port Id="8" Dir="OUT"/>
			<Port Id="7" Dir="OUT"/>
			<Port Id="6" Dir="OUT"/>
			<Port Id="5" Dir="OUT"/>
			<Port Id="4" Dir="OUT"/>
			<Port Id="3" Dir="OUT"/>
			<Port Id="2" Dir="OUT"/>
			<Port Id="1" Dir="OUT"/>
		</Bus>
		<Bus Id="Ram1Addr">
			<Port Id="17" Dir="OUT"/>
			<Port Id="16" Dir="OUT"/>
			<Port Id="15" Dir="OUT"/>
			<Port Id="14" Dir="OUT"/>
			<Port Id="13" Dir="OUT"/>
			<Port Id="12" Dir="OUT"/>
			<Port Id="11" Dir="OUT"/>
			<Port Id="10" Dir="OUT"/>
			<Port Id="9" Dir="OUT"/>
			<Port Id="8" Dir="OUT"/>
			<Port Id="7" Dir="OUT"/>
			<Port Id="6" Dir="OUT"/>
			<Port Id="5" Dir="OUT"/>
			<Port Id="4" Dir="OUT"/>
			<Port Id="3" Dir="OUT"/>
			<Port Id="2" Dir="OUT"/>
			<Port Id="1" Dir="OUT"/>
			<Port Id="0" Dir="OUT"/>
		</Bus>
		<Bus Id="LEDout">
			<Port Id="15" Dir="OUT"/>
			<Port Id="14" Dir="OUT"/>
			<Port Id="13" Dir="OUT"/>
			<Port Id="12" Dir="OUT"/>
			<Port Id="11" Dir="OUT"/>
			<Port Id="10" Dir="OUT"/>
			<Port Id="9" Dir="OUT"/>
			<Port Id="8" Dir="OUT"/>
			<Port Id="7" Dir="OUT"/>
			<Port Id="6" Dir="OUT"/>
			<Port Id="5" Dir="OUT"/>
			<Port Id="4" Dir="OUT"/>
			<Port Id="3" Dir="OUT"/>
			<Port Id="2" Dir="OUT"/>
			<Port Id="1" Dir="OUT"/>
			<Port Id="0" Dir="OUT"/>
		</Bus>
		<Port Id="clk" Dir="IN"/>
		<Port Id="Ram1WE" Dir="OUT"/>
		<Port Id="Ram2WE" Dir="OUT"/>
		<Port Id="rst" Dir="IN"/>
		<Port Id="data_ready" Dir="IN"/>
		<Port Id="FlashCE" Dir="OUT"/>
		<Port Id="FlashVpen" Dir="OUT"/>
		<Port Id="tbre" Dir="IN"/>
		<Port Id="Ram1EN" Dir="OUT"/>
		<Port Id="tsre" Dir="IN"/>
		<Port Id="FlashOE" Dir="OUT"/>
		<Port Id="Ram2EN" Dir="OUT"/>
		<Port Id="FlashRP" Dir="OUT"/>
		<Port Id="rdn" Dir="OUT"/>
		<Port Id="wrn" Dir="OUT"/>
		<Port Id="Ram1OE" Dir="OUT"/>
		<Port Id="FlashWE" Dir="OUT"/>
		<Port Id="FlashByte" Dir="OUT"/>
		<Port Id="Ram2OE" Dir="OUT"/>
	</Ifc>
</Interface>

